pymemes/__init__.py
pymemes/__main__.py
pymemes/cheems.py
pymemes-0.0.1.dist-info/LICENSE
pymemes-0.0.1.dist-info/METADATA
pymemes-0.0.1.dist-info/WHEEL
pymemes-0.0.1.dist-info/top_level.txt
pymemes-0.0.1.dist-info/RECORD
